{
  "ComponentIndexes": {},
  "ControlUniqueGuids": {},
  "ControlUniqueIds": {
    "Address_DataCard1": 126,
    "Age of Volunteers Needed_DataCard1": 131,
    "App": 1,
    "DataCardKey1": 97,
    "DataCardKey2": 102,
    "DataCardKey3": 107,
    "DataCardKey4": 112,
    "DataCardKey5": 117,
    "DataCardKey6": 122,
    "DataCardKey7": 127,
    "DataCardKey8": 132,
    "DataCardValue1": 98,
    "DataCardValue2": 103,
    "DataCardValue3": 108,
    "DataCardValue4": 113,
    "DataCardValue5": 118,
    "DataCardValue6": 123,
    "DataCardValue7": 128,
    "DataCardValue8": 133,
    "Description of Organization_DataCard1": 106,
    "ErrorMessage1": 99,
    "ErrorMessage2": 104,
    "ErrorMessage3": 109,
    "ErrorMessage4": 114,
    "ErrorMessage5": 119,
    "ErrorMessage6": 124,
    "ErrorMessage7": 129,
    "ErrorMessage8": 134,
    "Form1": 95,
    "Gallery3": 70,
    "galleryTemplate3": 71,
    "Host": 3,
    "Name of Organization_DataCard1": 101,
    "Name_DataCard1": 96,
    "NextArrow10": 156,
    "Phone Number_DataCard1": 121,
    "Primary Email_DataCard1": 111,
    "Rectangle10": 158,
    "Screen1": 4,
    "Screen2": 52,
    "Secondary Email_DataCard1": 116,
    "Separator10": 157,
    "StarVisible1": 100,
    "StarVisible2": 105,
    "StarVisible3": 110,
    "StarVisible4": 115,
    "StarVisible5": 120,
    "StarVisible6": 125,
    "StarVisible7": 130,
    "StarVisible8": 135,
    "Subtitle7": 155,
    "Title10": 154
  },
  "FunctionParamsInvariantScripts": {},
  "FunctionParamsInvariantScriptsOnInstances": {},
  "HeaderLastSavedDateTimeUTC": "04/26/2024 11:11:35",
  "IsLegacyComponentAllowGlobalScopeCase": false,
  "LocalConnectionIDReferences": {},
  "LocalDatabaseReferencesAsEmpty": false,
  "LocalResourceFileNames": {},
  "LocalResourceRootPaths": {},
  "OrderComponentMetadata": {},
  "OrderComponentTemplate": {},
  "OrderDataSource": {
    "CustomGallerySample": 3,
    "Database for Profiles": 4,
    "Database for Profiles\\cr864_databaseforprofiles_statecode": 1,
    "Database for Profiles\\cr864_databaseforprofiles_statuscode": 0,
    "Database for Profiles\\default.cds_cr864_databaseforprofiles_views": 2
  },
  "OrderGroupControls": {},
  "OrderPcfTemplate": {},
  "OrderTemplate": {},
  "OrderXMLTemplate": {
    "form": 0,
    "gallery": 3,
    "icon": 5,
    "label": 1,
    "rectangle": 4,
    "text": 2
  },
  "OverridablePropertiesEntry": {
    "Address_DataCard1": {},
    "Age of Volunteers Needed_DataCard1": {},
    "App": {},
    "DataCardKey1": {},
    "DataCardKey2": {},
    "DataCardKey3": {},
    "DataCardKey4": {},
    "DataCardKey5": {},
    "DataCardKey6": {},
    "DataCardKey7": {},
    "DataCardKey8": {},
    "DataCardValue1": {},
    "DataCardValue2": {},
    "DataCardValue3": {},
    "DataCardValue4": {},
    "DataCardValue5": {},
    "DataCardValue6": {},
    "DataCardValue7": {},
    "DataCardValue8": {},
    "Description of Organization_DataCard1": {},
    "ErrorMessage1": {},
    "ErrorMessage2": {},
    "ErrorMessage3": {},
    "ErrorMessage4": {},
    "ErrorMessage5": {},
    "ErrorMessage6": {},
    "ErrorMessage7": {},
    "ErrorMessage8": {},
    "Form1": {},
    "Gallery3": {},
    "galleryTemplate3": {},
    "Host": {},
    "Name of Organization_DataCard1": {},
    "Name_DataCard1": {},
    "NextArrow10": {},
    "Phone Number_DataCard1": {},
    "Primary Email_DataCard1": {},
    "Rectangle10": {},
    "Screen1": {},
    "Screen2": {},
    "Secondary Email_DataCard1": {},
    "Separator10": {},
    "StarVisible1": {},
    "StarVisible2": {},
    "StarVisible3": {},
    "StarVisible4": {},
    "StarVisible5": {},
    "StarVisible6": {},
    "StarVisible7": {},
    "StarVisible8": {},
    "Subtitle7": {},
    "Title10": {}
  },
  "PCFDynamicSchemaForIRRetrievalEntry": {},
  "PCFTemplateEntry": {},
  "PublishOrderIndices": {
    "Address_DataCard1": 31,
    "Age of Volunteers Needed_DataCard1": 36,
    "App": 0,
    "DataCardKey1": 3,
    "DataCardKey2": 8,
    "DataCardKey3": 13,
    "DataCardKey4": 18,
    "DataCardKey5": 23,
    "DataCardKey6": 28,
    "DataCardKey7": 33,
    "DataCardKey8": 38,
    "DataCardValue1": 4,
    "DataCardValue2": 9,
    "DataCardValue3": 14,
    "DataCardValue4": 19,
    "DataCardValue5": 24,
    "DataCardValue6": 29,
    "DataCardValue7": 34,
    "DataCardValue8": 39,
    "Description of Organization_DataCard1": 11,
    "ErrorMessage1": 5,
    "ErrorMessage2": 10,
    "ErrorMessage3": 15,
    "ErrorMessage4": 20,
    "ErrorMessage5": 25,
    "ErrorMessage6": 30,
    "ErrorMessage7": 35,
    "ErrorMessage8": 40,
    "Form1": 0,
    "Gallery3": 41,
    "galleryTemplate3": 42,
    "Host": 0,
    "Name of Organization_DataCard1": 6,
    "Name_DataCard1": 1,
    "NextArrow10": 0,
    "Phone Number_DataCard1": 26,
    "Primary Email_DataCard1": 16,
    "Rectangle10": 0,
    "Screen1": 0,
    "Screen2": 0,
    "Secondary Email_DataCard1": 21,
    "Separator10": 0,
    "StarVisible1": 2,
    "StarVisible2": 7,
    "StarVisible3": 12,
    "StarVisible4": 17,
    "StarVisible5": 22,
    "StarVisible6": 27,
    "StarVisible7": 32,
    "StarVisible8": 37,
    "Subtitle7": 0,
    "Title10": 0
  },
  "ResourcesJsonIndices": {
    "Image-SampleImage": 0
  },
  "RuleScreenIdWithoutScreen": {},
  "TemplateVersions": {},
  "VolatileProperties": {
    "AnalysisLoadTime": 0.406038,
    "ControlCount": {
      "form": 1,
      "gallery": 1,
      "galleryTemplate": 1,
      "icon": 1,
      "label": 25,
      "rectangle": 2,
      "screen": 2,
      "text": 8,
      "typedDataCard": 8
    },
    "DeserializationLoadTime": 1.0873016
  },
  "WasLocalDatabaseReferencesEmpty": false
}